test_mcp_connection.py
mcp_connection_checker-0.1.2.dist-info/METADATA
mcp_connection_checker-0.1.2.dist-info/WHEEL
mcp_connection_checker-0.1.2.dist-info/entry_points.txt
mcp_connection_checker-0.1.2.dist-info/top_level.txt
mcp_connection_checker-0.1.2.dist-info/RECORD
