Metadata-Version: 2.4
Name: mcp-connection-checker
Version: 0.1.2
Summary: MCPサーバーと対話し、定義されたツールを実行するためのコマンドラインインターフェース。
Requires-Python: >=3.8
Requires-Dist: twine>=6.1.0
Requires-Dist: anyio
Requires-Dist: mcp
